{
    "title": "The Best 2 AI Emoji Generator Tools in 2025",
    "summary": "Discover the power of expression with our AI Emoji Generator category! These innovative tools allow you to create personalized emojis that enhance your digital communication, making your messages more engaging and fun. Whether you're looking to add a unique touch to social media posts, enhance branding, or simply express yourself creatively, our AI-driven solutions cater to all your needs. Explore our curated selection of emoji generators today and elevate your conversations with custom designs that truly represent you! Dive in and start creating now!",
    "tools": [
        {
            "id": "530",
            "name": "Gencraft",
            "slug": "gencraft",
            "description": "Gencraft is an AI-powered platform that transforms text prompts into stunning digital art, images, videos, and emojis.",
            "icon": "/logo/gencraft.com.webp",
            "isFree": true,
            "categories": [
                "ai-emoji-generator"
            ]
        },
        {
            "id": "835",
            "name": "Bylo.ai",
            "slug": "bylo-ai",
            "description": "Bylo.ai is an AI-powered platform that transforms text prompts into high-quality images and offers creative photo editing tools.",
            "icon": "/logo/bylo.ai.webp",
            "isFree": true,
            "categories": [
                "ai-emoji-generator"
            ]
        }
    ]
}