{
    "title": "The Best 31 AI Face Swap Generator Tools in 2025",
    "summary": "Discover the power of creativity with our AI Face Swap Generator category! These innovative tools allow you to seamlessly swap faces in photos, enhancing your digital content with a fun and engaging twist. Perfect for social media enthusiasts, marketers, and content creators, our face swap generators offer quick, high-quality results that spark imagination and boost engagement. Explore our curated selection of AI tools today and transform your visuals effortlessly. Unleash your creativity—dive into the world of face swapping now!",
    "tools": [
        {
            "id": "73",
            "name": "AIFaceSwap",
            "slug": "aifaceswap",
            "description": "AIFaceSwap.io is a free online platform for seamlessly swapping faces in photos and videos using advanced AI technology.",
            "icon": "/logo/aifaceswap.io.webp",
            "isFree": true,
            "categories": [
                "ai-face-swap-generator"
            ]
        },
        {
            "id": "301",
            "name": "DreamFace",
            "slug": "dreamface",
            "description": "DreamFace is an AI-powered app that transforms photos into animated videos, avatars, and enhanced images with one-click simplicity.",
            "icon": "/logo/www.dreamfaceapp.com.webp",
            "isFree": true,
            "categories": [
                "ai-face-swap-generator"
            ]
        },
        {
            "id": "321",
            "name": "AKOOL",
            "slug": "akool",
            "description": "AKOOL is a generative AI platform for creating personalized visual marketing and advertising content.",
            "icon": "/logo/akool.com.webp",
            "isFree": true,
            "categories": [
                "ai-face-swap-generator"
            ]
        },
        {
            "id": "329",
            "name": "SwapFace",
            "slug": "swapface",
            "description": "SwapFace is an AI-powered platform for seamless face swapping in photos, videos, and GIFs, offering free and premium tools for creative content creation.",
            "icon": "/logo/www.swapfaces.ai.webp",
            "isFree": true,
            "categories": [
                "ai-face-swap-generator"
            ]
        },
        {
            "id": "354",
            "name": "MyIMG",
            "slug": "myimg",
            "description": "MyIMG is an AI-powered platform for transforming photos into cartoons, generating images from text, and editing visuals with features like face swapping and clothes removal.",
            "icon": "/logo/www.myimg.ai.webp",
            "isFree": true,
            "categories": [
                "ai-face-swap-generator"
            ]
        },
        {
            "id": "432",
            "name": "Aitubo",
            "slug": "aitubo",
            "description": "Aitubo is an AI-powered platform for generating high-quality images, videos, music, and avatars from text or images, catering to creators and artists.",
            "icon": "/logo/aitubo.ai.webp",
            "isFree": true,
            "categories": [
                "ai-face-swap-generator"
            ]
        },
        {
            "id": "444",
            "name": "Mango Animate",
            "slug": "mango-animate",
            "description": "Mango Animate provides user-friendly software for creating professional animated videos, whiteboard animations, and AI-driven video content.",
            "icon": "/logo/mangoanimate.com.webp",
            "isFree": true,
            "categories": [
                "ai-face-swap-generator"
            ]
        },
        {
            "id": "448",
            "name": "GoEnhance AI",
            "slug": "goenhance-ai",
            "description": "GoEnhance AI is an AI-powered platform for transforming and enhancing videos and images with advanced creative tools.",
            "icon": "/logo/www.goenhance.ai.webp",
            "isFree": true,
            "categories": [
                "ai-face-swap-generator"
            ]
        },
        {
            "id": "476",
            "name": "MimicPC",
            "slug": "mimicpc",
            "description": "MimicPC is a cloud-based platform offering instant access to AI tools for generating images, videos, audio, and training custom models.",
            "icon": "/logo/www.mimicpc.com.webp",
            "isFree": true,
            "categories": [
                "ai-face-swap-generator"
            ]
        },
        {
            "id": "484",
            "name": "BasedLabs",
            "slug": "basedlabs-ai",
            "description": "BasedLabs is an AI-powered platform for generating and editing images and videos, catering to creators and enthusiasts.",
            "icon": "/logo/www.basedlabs.ai.webp",
            "isFree": true,
            "categories": [
                "ai-face-swap-generator"
            ]
        },
        {
            "id": "495",
            "name": "Reface",
            "slug": "reface-ai",
            "description": "Reface is an AI-powered platform for creating realistic face swaps and animations in photos, videos, and GIFs.",
            "icon": "/logo/reface.ai.webp",
            "isFree": true,
            "categories": [
                "ai-face-swap-generator"
            ]
        },
        {
            "id": "508",
            "name": "Pincel",
            "slug": "pincel",
            "description": "Pincel is an AI-powered online image editing app that simplifies photo manipulation for users of all skill levels.",
            "icon": "/logo/pincel.app.webp",
            "isFree": true,
            "categories": [
                "ai-face-swap-generator"
            ]
        },
        {
            "id": "523",
            "name": "Deepfake Maker",
            "slug": "deepfake-maker",
            "description": "Deepfake Maker is an online AI-powered platform for creating face swaps and deepfake content in photos, videos, and GIFs.",
            "icon": "/logo/deepfakemaker.io.webp",
            "isFree": true,
            "categories": [
                "ai-face-swap-generator"
            ]
        },
        {
            "id": "541",
            "name": "Deepswap",
            "slug": "deepswap-ai",
            "description": "Deepswap is an AI-powered platform for seamless face swapping in videos, photos, and GIFs, offering realistic results for creative and professional use.",
            "icon": "/logo/www.deepswap.ai.webp",
            "isFree": false,
            "categories": [
                "ai-face-swap-generator"
            ]
        },
        {
            "id": "543",
            "name": "Grey's Secret Room",
            "slug": "greys-secret-room",
            "description": "Grey's Secret Room provides AI-powered tools for virtual clothing try-ons, undressing simulations, and face swaps for photos and videos.",
            "icon": "/logo/undressbaby.com.webp",
            "isFree": true,
            "categories": [
                "ai-face-swap-generator"
            ]
        },
        {
            "id": "544",
            "name": "DeepSwapper",
            "slug": "deepswapper",
            "description": "DeepSwapper is an AI-powered platform for seamless face swapping in photos and videos.",
            "icon": "/logo/www.deepswapper.com.webp",
            "isFree": true,
            "categories": [
                "ai-face-swap-generator"
            ]
        },
        {
            "id": "556",
            "name": "Deepfakes Web",
            "slug": "deepfakes-web",
            "description": "Deepfakes Web is an online platform that uses AI to create realistic face-swap videos for entertainment and creative purposes.",
            "icon": "/logo/deepfakesweb.com.webp",
            "isFree": true,
            "categories": [
                "ai-face-swap-generator"
            ]
        },
        {
            "id": "571",
            "name": "SoulGen",
            "slug": "soulgen",
            "description": "SoulGen is an AI-powered platform that generates stunning anime and realistic images or videos from text prompts, enabling users to create customized characters and artwork.",
            "icon": "/logo/www.soulgen.net.webp",
            "isFree": true,
            "categories": [
                "ai-face-swap-generator"
            ]
        },
        {
            "id": "602",
            "name": "Pikzels",
            "slug": "pikzels",
            "description": "Pikzels is an AI-powered platform for creating viral YouTube thumbnails and titles in seconds.",
            "icon": "/logo/pikzels.com.webp",
            "isFree": true,
            "categories": [
                "ai-face-swap-generator"
            ]
        },
        {
            "id": "650",
            "name": "VidMage",
            "slug": "vidmage-ai",
            "description": "VidMage is an AI-powered platform for seamless face swapping in photos, videos, and GIFs, offering realistic results for creative and entertainment purposes.",
            "icon": "/logo/vidmage.ai.webp",
            "isFree": true,
            "categories": [
                "ai-face-swap-generator"
            ]
        },
        {
            "id": "684",
            "name": "BeArt AI",
            "slug": "beart-ai",
            "description": "BeArt AI is a free online platform offering AI-driven tools for seamless face swapping and editing in photos, videos, and GIFs.",
            "icon": "/logo/beart.ai.webp",
            "isFree": true,
            "categories": [
                "ai-face-swap-generator"
            ]
        },
        {
            "id": "1346",
            "name": "Facy.ai",
            "slug": "facy-ai",
            "description": "Facy.ai is a cloud-based AI platform for face swapping in images and videos, providing free and premium tools for high-quality media editing and transformations.",
            "icon": "/logo/facy.ai.webp",
            "isFree": true,
            "categories": [
                "ai-face-swap-generator"
            ]
        },
        {
            "id": "757",
            "name": "ImgGen AI",
            "slug": "imggen-ai",
            "description": "ImgGen AI is a free online platform for generating and enhancing high-quality images using AI-driven tools.",
            "icon": "/logo/imggen.ai.webp",
            "isFree": true,
            "categories": [
                "ai-face-swap-generator"
            ]
        },
        {
            "id": "897",
            "name": "Fooocus",
            "slug": "fooocus",
            "description": "Fooocus is an AI-powered platform that simplifies image generation using Stable Diffusion, focusing on ease of use and high-quality outputs without complex configurations.",
            "icon": "/logo/fooocus.one.webp",
            "isFree": true,
            "categories": [
                "ai-face-swap-generator"
            ]
        },
        {
            "id": "1015",
            "name": "Swapface",
            "slug": "swapface-ai",
            "description": "Swapface is an AI-driven platform that allows users to perform real-time face swapping in videos and images for creative, entertainment, and professional applications.",
            "icon": "/logo/www.swapface.org.webp",
            "isFree": true,
            "categories": [
                "ai-face-swap-generator"
            ]
        },
        {
            "id": "1039",
            "name": "CrazyFaceAI",
            "slug": "crazyfaceai",
            "description": "CrazyFaceAI is an innovative platform that uses artificial intelligence to enable fun and creative face swapping and image manipulation for users seeking entertaining visual transformations.",
            "icon": "/logo/crazyfaceai.com.webp",
            "isFree": true,
            "categories": [
                "ai-face-swap-generator"
            ]
        },
        {
            "id": "1064",
            "name": "WeFaceSwap",
            "slug": "wefaceswap",
            "description": "WeFaceSwap is an AI-driven platform that enables users to easily swap faces in photos and videos for creative and entertainment purposes.",
            "icon": "/logo/www.wefaceswap.com.webp",
            "isFree": true,
            "categories": [
                "ai-face-swap-generator"
            ]
        },
        {
            "id": "1096",
            "name": "XJoy AI",
            "slug": "xjoy-ai",
            "description": "XJoy AI is an AI-powered platform specializing in NSFW content creation, virtual girlfriends, and image/video manipulations.",
            "icon": "/logo/www.xjoy.ai.webp",
            "isFree": true,
            "categories": [
                "ai-face-swap-generator"
            ]
        },
        {
            "id": "1126",
            "name": "VideoFaceSwap.io",
            "slug": "videofaceswap-io",
            "description": "VideoFaceSwap.io is an AI-driven platform that enables users to seamlessly swap faces in videos for creative, entertainment, or professional purposes.",
            "icon": "/logo/videofaceswap.io.webp",
            "isFree": true,
            "categories": [
                "ai-face-swap-generator"
            ]
        },
        {
            "id": "1388",
            "name": "FaceSwapVideo.ai",
            "slug": "faceswapvideo-ai",
            "description": "FaceSwapVideo.ai is an AI-powered platform that enables users to easily swap faces in videos for creative, entertainment, or professional purposes.",
            "icon": "/logo/faceswapvideo.ai.webp",
            "isFree": true,
            "categories": [
                "ai-face-swap-generator"
            ]
        },
        {
            "id": "1443",
            "name": "Remaker AI",
            "slug": "remaker-ai",
            "description": "Remaker AI is an online platform that leverages artificial intelligence for advanced image editing, face swapping, and creative content generation.",
            "icon": "/logo/remaker.ai.webp",
            "isFree": true,
            "categories": [
                "ai-face-swap-generator"
            ]
        }
    ]
}