{
    "title": "The Best 82 AI Music Generator Tools in 2025",
    "summary": "Discover the transformative world of AI Music Generators, where creativity meets cutting-edge technology. These innovative tools empower musicians, content creators, and hobbyists to effortlessly compose unique soundtracks, melodies, and beats tailored to their projects. With features like genre customization and real-time collaboration, you can elevate your musical endeavors without the steep learning curve. Whether you're crafting background music for videos or exploring new sonic landscapes, our curated selection of AI music generators is here to inspire. Dive in and explore the tools that will revolutionize your music-making experience today!",
    "tools": [
        {
            "id": "105",
            "name": "Shutterstock",
            "slug": "shutterstock",
            "description": "Shutterstock provides a global marketplace for licensing royalty-free images, videos, and music for creative projects.",
            "icon": "/logo/shutterstock.com.webp",
            "isFree": true,
            "categories": [
                "ai-music-generator"
            ]
        },
        {
            "id": "33",
            "name": "DeepAI",
            "slug": "deepai",
            "description": "DeepAI provides AI-powered tools for generating and editing creative content like images, videos, music, and text.",
            "icon": "/logo/deepai.org.webp",
            "isFree": true,
            "categories": [
                "ai-music-generator"
            ]
        },
        {
            "id": "134",
            "name": "Wondershare",
            "slug": "wondershare",
            "description": "Wondershare provides AI-powered software solutions for video editing, PDF management, data recovery, and mobile device management to enhance creativity and productivity.",
            "icon": "/logo/wondershare.com.webp",
            "isFree": true,
            "categories": [
                "ai-music-generator"
            ]
        },
        {
            "id": "159",
            "name": "Riffusion",
            "slug": "riffusion",
            "description": "Riffusion is an AI-powered platform that generates music from text prompts, enabling users to create unique audio compositions effortlessly.",
            "icon": "/logo/www.riffusion.com.webp",
            "isFree": true,
            "categories": [
                "ai-music-generator"
            ]
        },
        {
            "id": "184",
            "name": "Replicate",
            "slug": "replicate",
            "description": "Replicate is a platform for running, sharing, and deploying machine learning models in the cloud.",
            "icon": "/logo/replicate.com.webp",
            "isFree": true,
            "categories": [
                "ai-music-generator"
            ]
        },
        {
            "id": "193",
            "name": "Moises",
            "slug": "moises",
            "description": "Moises uses AI to separate, edit, and enhance audio tracks for musicians and producers.",
            "icon": "/logo/moises.ai.webp",
            "isFree": true,
            "categories": [
                "ai-music-generator"
            ]
        },
        {
            "id": "197",
            "name": "Udio",
            "slug": "udio",
            "description": "Udio is an AI-powered platform for creating high-quality, royalty-free music tailored to user preferences.",
            "icon": "/logo/www.udio.com.webp",
            "isFree": true,
            "categories": [
                "ai-music-generator"
            ]
        },
        {
            "id": "205",
            "name": "Luvvoice",
            "slug": "luvvoice",
            "description": "Luvvoice provides AI-powered text-to-speech and voice cloning for creating realistic audio content.",
            "icon": "/logo/luvvoice.com.webp",
            "isFree": true,
            "categories": [
                "ai-music-generator"
            ]
        },
        {
            "id": "210",
            "name": "Lalal.ai",
            "slug": "lalal-ai",
            "description": "Lalal.ai is an AI-powered audio processing platform specializing in vocal and instrumental track separation and enhancement.",
            "icon": "/logo/www.lalal.ai.webp",
            "isFree": true,
            "categories": [
                "ai-music-generator"
            ]
        },
        {
            "id": "232",
            "name": "Mureka",
            "slug": "mureka",
            "description": "Mureka is an AI-powered platform for creating and managing music and audio content.",
            "icon": "/logo/www.mureka.ai.webp",
            "isFree": true,
            "categories": [
                "ai-music-generator"
            ]
        },
        {
            "id": "100",
            "name": "Brain.fm",
            "slug": "brain-fm",
            "description": "Brain.fm provides science-backed functional music to enhance focus, relaxation, and sleep.",
            "icon": "/logo/brain.fm.webp",
            "isFree": true,
            "categories": [
                "ai-music-generator"
            ]
        },
        {
            "id": "253",
            "name": "Fish Audio",
            "slug": "fish-audio",
            "description": "Fish Audio provides AI-powered tools for music creation, voice generation, and audio editing.",
            "icon": "/logo/fish.audio.webp",
            "isFree": true,
            "categories": [
                "ai-music-generator"
            ]
        },
        {
            "id": "330",
            "name": "Revid AI",
            "slug": "revid-ai",
            "description": "Revid AI is an AI-powered platform for creating viral short videos for social media platforms like TikTok, Instagram, and YouTube.",
            "icon": "/logo/www.revid.ai.webp",
            "isFree": true,
            "categories": [
                "ai-music-generator"
            ]
        },
        {
            "id": "378",
            "name": "FakeYou",
            "slug": "fakeyou",
            "description": "FakeYou is an AI-powered platform that generates realistic text-to-speech audio and voice conversions using celebrity and character voices.",
            "icon": "/logo/fakeyou.com.webp",
            "isFree": true,
            "categories": [
                "ai-music-generator"
            ]
        },
        {
            "id": "389",
            "name": "Fadr",
            "slug": "fadr",
            "description": "Fadr is an AI-powered music creation platform for remixing, stem separation, and DJing.",
            "icon": "/logo/fadr.com.webp",
            "isFree": true,
            "categories": [
                "ai-music-generator"
            ]
        },
        {
            "id": "391",
            "name": "Kits AI",
            "slug": "kits-ai",
            "description": "Kits AI provides studio-quality AI music tools for producers to streamline workflows and enhance music creation.",
            "icon": "/logo/www.kits.ai.webp",
            "isFree": true,
            "categories": [
                "ai-music-generator"
            ]
        },
        {
            "id": "408",
            "name": "Stability AI",
            "slug": "stability-ai",
            "description": "Stability AI provides open-source generative AI tools for creating images, videos, audio, and 3D content.",
            "icon": "/logo/stability.ai.webp",
            "isFree": true,
            "categories": [
                "ai-music-generator"
            ]
        },
        {
            "id": "418",
            "name": "eMastered",
            "slug": "emastered",
            "description": "eMastered provides AI-powered online audio mastering services created by Grammy-winning engineers to enhance music tracks instantly.",
            "icon": "/logo/emastered.com.webp",
            "isFree": true,
            "categories": [
                "ai-music-generator"
            ]
        },
        {
            "id": "432",
            "name": "Aitubo",
            "slug": "aitubo",
            "description": "Aitubo is an AI-powered platform for generating high-quality images, videos, music, and avatars from text or images, catering to creators and artists.",
            "icon": "/logo/aitubo.ai.webp",
            "isFree": true,
            "categories": [
                "ai-music-generator"
            ]
        },
        {
            "id": "437",
            "name": "Podcastle",
            "slug": "podcastle-ai",
            "description": "Podcastle is an AI-powered platform for creating, editing, and distributing professional-quality podcasts and videos directly in your browser.",
            "icon": "/logo/podcastle.ai.webp",
            "isFree": true,
            "categories": [
                "ai-music-generator"
            ]
        },
        {
            "id": "475",
            "name": "Chatbox AI",
            "slug": "chatbox-ai",
            "description": "Chatbox AI is a versatile AI client application and intelligent assistant enhancing productivity across multiple platforms.",
            "icon": "/logo/chatboxai.app.webp",
            "isFree": true,
            "categories": [
                "ai-music-generator"
            ]
        },
        {
            "id": "476",
            "name": "MimicPC",
            "slug": "mimicpc",
            "description": "MimicPC is a cloud-based platform offering instant access to AI tools for generating images, videos, audio, and training custom models.",
            "icon": "/logo/www.mimicpc.com.webp",
            "isFree": true,
            "categories": [
                "ai-music-generator"
            ]
        },
        {
            "id": "505",
            "name": "AI Song Maker",
            "slug": "ai-song-maker",
            "description": "AI Song Maker is an AI-powered platform for creating royalty-free songs from text prompts or melodies.",
            "icon": "/logo/www.aisongmaker.io.webp",
            "isFree": true,
            "categories": [
                "ai-music-generator"
            ]
        },
        {
            "id": "522",
            "name": "SOUNDRAW",
            "slug": "soundraw",
            "description": "SOUNDRAW is an AI-powered music generator that creates customizable, royalty-free tracks for creators and businesses.",
            "icon": "/logo/soundraw.io.webp",
            "isFree": true,
            "categories": [
                "ai-music-generator"
            ]
        },
        {
            "id": "548",
            "name": "AIMusic.so",
            "slug": "aimusic-so",
            "description": "AIMusic.so is an AI-powered platform for generating royalty-free music, lyrics, sound effects, and MP4 lyric videos from text prompts, accessible without sign-up.",
            "icon": "/logo/aimusic.so.webp",
            "isFree": true,
            "categories": [
                "ai-music-generator"
            ]
        },
        {
            "id": "562",
            "name": "Output",
            "slug": "output",
            "description": "Output provides innovative music creation tools and software for musicians and producers.",
            "icon": "/logo/output.com.webp",
            "isFree": true,
            "categories": [
                "ai-music-generator"
            ]
        },
        {
            "id": "565",
            "name": "Musicfy",
            "slug": "musicfy",
            "description": "Musicfy is an AI-powered platform for creating and customizing music with voice cloning and text-to-music features.",
            "icon": "/logo/musicfy.lol.webp",
            "isFree": true,
            "categories": [
                "ai-music-generator"
            ]
        },
        {
            "id": "572",
            "name": "Songtell",
            "slug": "songtell",
            "description": "Songtell uses AI to analyze and uncover the hidden meanings behind song lyrics, enhancing music appreciation for fans and educators.",
            "icon": "/logo/songtell.com.webp",
            "isFree": true,
            "categories": [
                "ai-music-generator"
            ]
        },
        {
            "id": "574",
            "name": "Brev AI",
            "slug": "brev-ai",
            "description": "Brev AI is an AI-powered music generator that transforms text prompts into professional-quality, royalty-free music tracks.",
            "icon": "/logo/brev.ai.webp",
            "isFree": true,
            "categories": [
                "ai-music-generator"
            ]
        },
        {
            "id": "613",
            "name": "Uberduck",
            "slug": "uberduck-ai",
            "description": "Uberduck is an AI-powered platform for generating realistic synthetic vocals, text-to-speech, and voice cloning for music, voiceovers, and content creation.",
            "icon": "/logo/www.uberduck.ai.webp",
            "isFree": true,
            "categories": [
                "ai-music-generator"
            ]
        },
        {
            "id": "628",
            "name": "AIMusicGen.ai",
            "slug": "aimusicgen-ai",
            "description": "AIMusicGen.ai is an AI-powered platform that instantly transforms text or lyrics into high-quality, royalty-free songs.",
            "icon": "/logo/aimusicgen.ai.webp",
            "isFree": true,
            "categories": [
                "ai-music-generator"
            ]
        },
        {
            "id": "667",
            "name": "AIVA",
            "slug": "aiva",
            "description": "AIVA is an AI-powered music generation platform that creates original compositions for various creative projects.",
            "icon": "/logo/www.aiva.ai.webp",
            "isFree": true,
            "categories": [
                "ai-music-generator"
            ]
        },
        {
            "id": "685",
            "name": "AutoShorts.ai",
            "slug": "autoshorts-ai",
            "description": "AutoShorts.ai is an AI-powered platform that automates the creation, scheduling, and posting of faceless videos for TikTok and YouTube to grow social media channels effortlessly.",
            "icon": "/logo/autoshorts.ai.webp",
            "isFree": true,
            "categories": [
                "ai-music-generator"
            ]
        },
        {
            "id": "688",
            "name": "AI Song Generator",
            "slug": "ai-song-generator",
            "description": "AI Song Generator is a free online tool that uses AI to create custom songs from text prompts or lyrics.",
            "icon": "/logo/aisonggenerator.ai.webp",
            "isFree": true,
            "categories": [
                "ai-music-generator"
            ]
        },
        {
            "id": "697",
            "name": "Wondercraft",
            "slug": "wondercraft-ai",
            "description": "Wondercraft is an AI-powered platform for creating studio-quality podcasts, audiobooks, and ads effortlessly.",
            "icon": "/logo/www.wondercraft.ai.webp",
            "isFree": true,
            "categories": [
                "ai-music-generator"
            ]
        },
        {
            "id": "712",
            "name": "Mubert",
            "slug": "mubert",
            "description": "Mubert is an AI-powered platform that generates royalty-free music for content creators, streamers, and businesses.",
            "icon": "/logo/mubert.com.webp",
            "isFree": true,
            "categories": [
                "ai-music-generator"
            ]
        },
        {
            "id": "745",
            "name": "Soundverse AI",
            "slug": "soundverse-ai",
            "description": "Soundverse AI is an AI-powered music creation platform that enables users to generate and customize high-quality, royalty-free music effortlessly.",
            "icon": "/logo/www.soundverse.ai.webp",
            "isFree": true,
            "categories": [
                "ai-music-generator"
            ]
        },
        {
            "id": "763",
            "name": "Beatoven.ai",
            "slug": "beatoven-ai",
            "description": "Beatoven.ai is an AI-powered platform that generates royalty-free, customizable background music for videos, podcasts, and games.",
            "icon": "/logo/www.beatoven.ai.webp",
            "isFree": true,
            "categories": [
                "ai-music-generator"
            ]
        },
        {
            "id": "770",
            "name": "SongGenerator.io",
            "slug": "songgenerator-io",
            "description": "SongGenerator.io is an AI-powered platform that creates royalty-free music and songs from text prompts for creators and musicians.",
            "icon": "/logo/songgenerator.io.webp",
            "isFree": true,
            "categories": [
                "ai-music-generator"
            ]
        },
        {
            "id": "771",
            "name": "Boomy",
            "slug": "boomy",
            "description": "Boomy is an AI-powered platform that enables users to create and monetize original music effortlessly.",
            "icon": "/logo/boomy.com.webp",
            "isFree": true,
            "categories": [
                "ai-music-generator"
            ]
        },
        {
            "id": "790",
            "name": "VoiceDub",
            "slug": "voicedub-ai",
            "description": "VoiceDub is an AI-powered platform for creating high-quality voice covers, voiceovers, and audio content using advanced voice cloning and text-to-speech technologies.",
            "icon": "/logo/voicedub.ai.webp",
            "isFree": true,
            "categories": [
                "ai-music-generator"
            ]
        },
        {
            "id": "796",
            "name": "Soundful",
            "slug": "soundful",
            "description": "Soundful is an AI-powered music creation platform that generates royalty-free, studio-quality tracks for creators and businesses.",
            "icon": "/logo/soundful.com.webp",
            "isFree": true,
            "categories": [
                "ai-music-generator"
            ]
        },
        {
            "id": "805",
            "name": "AI/ML API",
            "slug": "aiml-api",
            "description": "AI/ML API provides access to over 300 AI models through a single, unified API for developers and businesses.",
            "icon": "/logo/aimlapi.com.webp",
            "isFree": true,
            "categories": [
                "ai-music-generator"
            ]
        },
        {
            "id": "825",
            "name": "SendFame",
            "slug": "sendfame",
            "description": "SendFame is an AI-powered platform for creating personalized celebrity video messages and custom music for personal and parody use.",
            "icon": "/logo/sendfame.com.webp",
            "isFree": true,
            "categories": [
                "ai-music-generator"
            ]
        },
        {
            "id": "855",
            "name": "ILoveSong.ai",
            "slug": "ilovesong-ai",
            "description": "ILoveSong.ai is an AI-driven platform that generates personalized songs and music based on user prompts and preferences.",
            "icon": "/logo/ilovesong.ai.webp",
            "isFree": true,
            "categories": [
                "ai-music-generator"
            ]
        },
        {
            "id": "860",
            "name": "MusicGeneratorAI",
            "slug": "musicgeneratorai",
            "description": "MusicGeneratorAI is an AI-driven platform that enables users to generate custom music tracks from text prompts and creative inputs.",
            "icon": "/logo/musicgeneratorai.com.webp",
            "isFree": true,
            "categories": [
                "ai-music-generator"
            ]
        },
        {
            "id": "883",
            "name": "Melobytes",
            "slug": "melobytes",
            "description": "Melobytes is an innovative online platform providing a wide array of AI-powered tools for creative content generation in music, audio, images, and more.",
            "icon": "/logo/melobytes.com.webp",
            "isFree": true,
            "categories": [
                "ai-music-generator"
            ]
        },
        {
            "id": "905",
            "name": "LoveVoice AI",
            "slug": "lovevoice-ai",
            "description": "LoveVoice.ai is an AI-powered platform that enables users to generate personalized, emotional voice messages for romantic or affectionate purposes.",
            "icon": "/logo/lovevoice.ai.webp",
            "isFree": true,
            "categories": [
                "ai-music-generator"
            ]
        },
        {
            "id": "906",
            "name": "Amped Studio",
            "slug": "amped-studio",
            "description": "Amped Studio is an online digital audio workstation that enables users to create, edit, and collaborate on music productions directly in their web browser.",
            "icon": "/logo/ampedstudio.com.webp",
            "isFree": true,
            "categories": [
                "ai-music-generator"
            ]
        },
        {
            "id": "928",
            "name": "Splitter.ai",
            "slug": "splitter-ai",
            "description": "Splitter.ai is an AI-driven platform that separates mixed audio tracks into individual stems like vocals, drums, bass, and instruments for music production and remixing.",
            "icon": "/logo/splitter.ai.webp",
            "isFree": true,
            "categories": [
                "ai-music-generator"
            ]
        },
        {
            "id": "933",
            "name": "Vocalize.fm",
            "slug": "vocalize-fm",
            "description": "Vocalize.fm is an AI-driven platform that enables users to generate high-quality podcasts and audio content from text using advanced voice synthesis technology.",
            "icon": "/logo/www.vocalize.fm.webp",
            "isFree": true,
            "categories": [
                "ai-music-generator"
            ]
        },
        {
            "id": "938",
            "name": "StockTune",
            "slug": "stocktune",
            "description": "StockTune is an AI-powered platform that generates royalty-free music tracks for creators, offering customizable and high-quality audio content.",
            "icon": "/logo/stocktune.com.webp",
            "isFree": true,
            "categories": [
                "ai-music-generator"
            ]
        },
        {
            "id": "977",
            "name": "Suno",
            "slug": "suno-ai",
            "description": "Suno is an AI-powered platform that enables users to generate original music and songs from text prompts.",
            "icon": "/logo/sunoai.ai.webp",
            "isFree": true,
            "categories": [
                "ai-music-generator"
            ]
        },
        {
            "id": "1000",
            "name": "Ryne AI",
            "slug": "ryne-ai",
            "description": "Ryne AI is an innovative platform that uses artificial intelligence to generate rhymes, lyrics, and creative writing content for users in music and poetry.",
            "icon": "/logo/ryne.ai.webp",
            "isFree": true,
            "categories": [
                "ai-music-generator"
            ]
        },
        {
            "id": "1009",
            "name": "Maestro Labs",
            "slug": "maestro-labs",
            "description": "Maestro Labs is an AI-driven platform specializing in music and audio generation, editing, and analysis to empower creators with innovative tools.",
            "icon": "/logo/www.maestrolabs.com.webp",
            "isFree": true,
            "categories": [
                "ai-music-generator"
            ]
        },
        {
            "id": "1042",
            "name": "AI Music Generator",
            "slug": "ai-music-generator",
            "description": "AI Music Generator is an online platform that uses artificial intelligence to create custom music tracks based on user inputs like text descriptions, genres, and moods.",
            "icon": "/logo/ai-music-generator.ai.webp",
            "isFree": true,
            "categories": [
                "ai-music-generator"
            ]
        },
        {
            "id": "1125",
            "name": "Cyanite.ai",
            "slug": "cyanite-ai",
            "description": "Cyanite.ai is an AI-driven platform specializing in music analysis, tagging, and search to empower music professionals with intelligent metadata extraction and discovery tools.",
            "icon": "/logo/cyanite.ai.webp",
            "isFree": true,
            "categories": [
                "ai-music-generator"
            ]
        },
        {
            "id": "1163",
            "name": "Woxo",
            "slug": "woxo",
            "description": "Woxo is an AI-driven platform that simplifies video creation, allowing users to generate engaging short-form videos for social media using text prompts and customizable templates.",
            "icon": "/logo/woxo.tech.webp",
            "isFree": true,
            "categories": [
                "ai-music-generator"
            ]
        },
        {
            "id": "1179",
            "name": "Respeecher",
            "slug": "respeecher",
            "description": "Respeecher is an AI-powered platform specializing in voice cloning and conversion for film, animation, gaming, and content creation.",
            "icon": "/logo/www.respeecher.com.webp",
            "isFree": false,
            "categories": [
                "ai-music-generator"
            ]
        },
        {
            "id": "1188",
            "name": "LyricStudio",
            "slug": "lyricstudio",
            "description": "LyricStudio is an AI-powered platform designed to help songwriters generate creative lyrics, overcome writer's block, and streamline the songwriting process.",
            "icon": "/logo/lyricstudio.net.webp",
            "isFree": true,
            "categories": [
                "ai-music-generator"
            ]
        },
        {
            "id": "1203",
            "name": "Controlla",
            "slug": "controlla",
            "description": "Controlla is a music tech platform using AI to create personalized singing voices, generate choirs, and enable interactive music experiences.",
            "icon": "/logo/www.controlla.xyz.webp",
            "isFree": true,
            "categories": [
                "ai-music-generator"
            ]
        },
        {
            "id": "1429",
            "name": "AI Jingle Maker",
            "slug": "ai-jingle-maker",
            "description": "AI Jingle Maker is an innovative platform that leverages artificial intelligence to create custom musical jingles for advertising, branding, and entertainment purposes.",
            "icon": "/logo/www.aijinglemaker.com.webp",
            "isFree": true,
            "categories": [
                "ai-music-generator"
            ]
        },
        {
            "id": "1421",
            "name": "Voice Isolator",
            "slug": "voice-isolator",
            "description": "Voice Isolator is an AI-powered online tool designed to separate vocals from audio tracks and remove background noise for enhanced audio editing.",
            "icon": "/logo/www.voiceisolator.org.webp",
            "isFree": true,
            "categories": [
                "ai-music-generator"
            ]
        },
        {
            "id": "1364",
            "name": "VibeScan",
            "slug": "vibescan",
            "description": "VibeScan is an AI-powered platform that analyzes the emotional tone and vibe of digital content to help users understand social dynamics and sentiment.",
            "icon": "/logo/vibescan.io.webp",
            "isFree": true,
            "categories": [
                "ai-music-generator"
            ]
        },
        {
            "id": "1338",
            "name": "Suno API",
            "slug": "suno-api",
            "description": "Suno API is an AI-powered music generation platform offering developers a scalable API to create studio-quality vocal and instrumental tracks from text prompts.",
            "icon": "/logo/sunoapi.com.webp",
            "isFree": true,
            "categories": [
                "ai-music-generator"
            ]
        },
        {
            "id": "1397",
            "name": "ElevenMusic",
            "slug": "elevenmusic-ai",
            "description": "ElevenMusic.ai is an AI-powered platform for generating and editing music tracks using advanced artificial intelligence.",
            "icon": "/logo/elevenmusic.ai.webp",
            "isFree": true,
            "categories": [
                "ai-music-generator"
            ]
        },
        {
            "id": "1391",
            "name": "Eleven Music AI",
            "slug": "eleven-music-ai",
            "description": "Eleven Music AI is an innovative platform that leverages artificial intelligence to generate, customize, and produce high-quality music tracks for creators and musicians.",
            "icon": "/logo/elevenmusicai.io.webp",
            "isFree": true,
            "categories": [
                "ai-music-generator"
            ]
        },
        {
            "id": "1386",
            "name": "Spotboi.ai",
            "slug": "spotboi-ai",
            "description": "Spotboi.ai is an AI-powered platform that generates realistic voiceovers, audio content, and music for creative and professional use.",
            "icon": "/logo/spotboi.ai.webp",
            "isFree": true,
            "categories": [
                "ai-music-generator"
            ]
        },
        {
            "id": "1399",
            "name": "MusicEleven AI",
            "slug": "musiceleven-ai",
            "description": "MusicEleven AI is an innovative platform that uses artificial intelligence to generate custom music tracks based on user inputs like text prompts, moods, or genres.",
            "icon": "/logo/musiceleven.ai.webp",
            "isFree": true,
            "categories": [
                "ai-music-generator"
            ]
        },
        {
            "id": "1409",
            "name": "Verbite",
            "slug": "verbite",
            "description": "Verbite is an AI-powered platform specializing in voice generation and conversion for content creators, educators, and businesses.",
            "icon": "/logo/verbite.com.webp",
            "isFree": true,
            "categories": [
                "ai-music-generator"
            ]
        },
        {
            "id": "1413",
            "name": "Eleven Music AI",
            "slug": "eleven-music-ai-com",
            "description": "Eleven Music AI is an innovative platform that uses artificial intelligence to generate, customize, and produce high-quality music tracks for creators and musicians.",
            "icon": "/logo/elevenmusicai.com.webp",
            "isFree": true,
            "categories": [
                "ai-music-generator"
            ]
        },
        {
            "id": "1335",
            "name": "Reeroll",
            "slug": "reeroll",
            "description": "Reeroll is an AI-driven platform that enables users to generate, edit, and customize videos using advanced artificial intelligence tools.",
            "icon": "/logo/reeroll.com.webp",
            "isFree": true,
            "categories": [
                "ai-music-generator"
            ]
        },
        {
            "id": "1297",
            "name": "Create Anything",
            "slug": "create-anything",
            "description": "Create Anything is an AI-powered platform that enables users to generate diverse digital content, from text and images to music and code, using advanced artificial intelligence tools.",
            "icon": "/logo/www.createanything.com.webp",
            "isFree": true,
            "categories": [
                "ai-music-generator"
            ]
        },
        {
            "id": "1280",
            "name": "SongAgent",
            "slug": "songagent",
            "description": "SongAgent is an AI-powered platform designed to assist musicians in creating, editing, and learning songs through intelligent tools.",
            "icon": "/logo/songagent.com.webp",
            "isFree": true,
            "categories": [
                "ai-music-generator"
            ]
        },
        {
            "id": "1253",
            "name": "AI Fiesta",
            "slug": "ai-fiesta",
            "description": "AI Fiesta is an AI-powered platform designed to revolutionize party planning and celebrations by generating creative ideas, invitations, and entertainment content.",
            "icon": "/logo/aifiesta.ai.webp",
            "isFree": true,
            "categories": [
                "ai-music-generator"
            ]
        },
        {
            "id": "1435",
            "name": "Veo 3",
            "slug": "veo-3-ai",
            "description": "Veo 3 is an AI tool that generates videos with synchronized audio, including sound effects, dialogue, and ambient noise, using text descriptions or image references.",
            "icon": "/logo/veo3.ai.webp",
            "isFree": true,
            "categories": [
                "ai-music-generator"
            ]
        },
        {
            "id": "13",
            "name": "Suno",
            "slug": "suno",
            "description": "Suno is an AI-powered platform that transforms text prompts into original music and songs.",
            "icon": "/logo/suno.com.webp",
            "isFree": true,
            "categories": [
                "ai-music-generator"
            ]
        },
        {
            "id": "1441",
            "name": "Vocal Remover",
            "slug": "vocal-remover",
            "description": "VocalRemover.org is an online tool that uses AI to separate vocals from music tracks, creating instrumentals, karaoke versions, and more.",
            "icon": "/logo/vocalremover.org.webp",
            "isFree": true,
            "categories": [
                "ai-music-generator"
            ]
        },
        {
            "id": "1317",
            "name": "Vaanee",
            "slug": "vaanee",
            "description": "Vaanee Labs offers AI-driven voice cloning, text-to-speech, speech-to-speech translation, and video dubbing services with multilingual and hyper-realistic voice generation capabilities.",
            "icon": "/logo/www.vaanee.co.webp",
            "isFree": false,
            "categories": [
                "ai-music-generator"
            ]
        },
        {
            "id": "941",
            "name": "PlusVibe",
            "slug": "plusvibe-ai",
            "description": "PlusVibe is an AI-powered platform that generates personalized music and positive vibes to enhance user mood and creativity.",
            "icon": "/logo/www.plusvibe.ai.webp",
            "isFree": true,
            "categories": [
                "ai-music-generator"
            ]
        },
        {
            "id": "62",
            "name": "NotebookLM",
            "slug": "notebooklm",
            "description": "NotebookLM is an AI-powered research and note-taking tool that helps users summarize, analyze, and interact with complex information from various sources.",
            "icon": "/logo/notebooklm.google.webp",
            "isFree": true,
            "categories": [
                "ai-music-generator"
            ]
        },
        {
            "id": "19",
            "name": "Doubao",
            "slug": "doubao",
            "description": "Doubao is an AI-powered conversational assistant platform by ByteDance, offering multimodal solutions for text, image, and audio tasks.",
            "icon": "/logo/doubao.com.webp",
            "isFree": true,
            "categories": [
                "ai-music-generator"
            ]
        }
    ]
}